README.md
setup.py
AirzoneCloud/AirzoneCloud.py
AirzoneCloud/Site.py
AirzoneCloud/System.py
AirzoneCloud/Zone.py
AirzoneCloud/__init__.py
AirzoneCloud/contants.py
AirzoneCloudfix.egg-info/PKG-INFO
AirzoneCloudfix.egg-info/SOURCES.txt
AirzoneCloudfix.egg-info/dependency_links.txt
AirzoneCloudfix.egg-info/requires.txt
AirzoneCloudfix.egg-info/top_level.txt