Metadata-Version: 2.1
Name: AirzoneCloudfix
Version: 0.5.0.1
Summary: Python3 library for Airzone Cloud API
Home-page: https://github.com/ukrolelo/AirzoneCloud
Author: ukrolelo
Author-email: max13fr@yozo.fr
License: UNKNOWN
Keywords: airzone,airzonecloud,api
Platform: UNKNOWN
Classifier: Development Status :: 4 - Beta
Classifier: Programming Language :: Python :: 3
Classifier: License :: OSI Approved :: MIT License
Classifier: Operating System :: OS Independent
Requires-Python: >=3.5
